tutorphpmyadmin/__about__.py
tutorphpmyadmin/__init__.py
tutorphpmyadmin/plugin.py
tutorphpmyadmin/patches/caddyfile
tutorphpmyadmin/patches/k8s-deployments
tutorphpmyadmin/patches/k8s-services
tutorphpmyadmin/patches/kustomization-configmapgenerator
tutorphpmyadmin/patches/local-docker-compose-caddy-aliases
tutorphpmyadmin/patches/local-docker-compose-dev-services
tutorphpmyadmin/patches/local-docker-compose-services
tutorphpmyadmin/templates/phpmyadmin/apps/config/pma_config.php
tutorphpmyadmin/templates/phpmyadmin/apps/config/pma_php.ini
tutorphpmyadmin/templates/phpmyadmin/build/.gitignore
tutorphpmyadmin/templates/phpmyadmin/tasks/lms/.gitignore
tutor_contrib_phpmyadmin-2.0.0.dist-info/METADATA
tutor_contrib_phpmyadmin-2.0.0.dist-info/WHEEL
tutor_contrib_phpmyadmin-2.0.0.dist-info/entry_points.txt
tutor_contrib_phpmyadmin-2.0.0.dist-info/licenses/LICENSE.txt
tutor_contrib_phpmyadmin-2.0.0.dist-info/RECORD
