Metadata-Version: 2.4
Name: tutor-contrib-phpmyadmin
Version: 2.0.0
Summary: phpmyadmin plugin for Tutor
Project-URL: Code, https://github.com/CodeWithEmad/tutor-contrib-phpmyadmin
Project-URL: Issues, https://github.com/CodeWithEmad/tutor-contrib-phpmyadmin/issues
Project-URL: Changelog, https://github.com/CodeWithEmad/tutor-contrib-phpmyadmin/blob/master/CHANGELOG.md
Author: Emad Rad
Author-email: codewithemad@gmail.com
License: AGPL-3.0-only
License-File: LICENSE.txt
Classifier: Development Status :: 5 - Production/Stable
Classifier: Intended Audience :: Developers
Classifier: License :: OSI Approved :: GNU Affero General Public License v3
Classifier: Operating System :: OS Independent
Classifier: Programming Language :: Python
Classifier: Programming Language :: Python :: 3.9
Classifier: Programming Language :: Python :: 3.10
Classifier: Programming Language :: Python :: 3.11
Classifier: Programming Language :: Python :: 3.12
Requires-Python: >=3.9
Requires-Dist: tutor<20.0.0,>=15.0.0
Provides-Extra: dev
Requires-Dist: black; extra == 'dev'
Requires-Dist: pylint; extra == 'dev'
Requires-Dist: tutor[dev]<20.0.0,>=15.0.0; extra == 'dev'
